AlgorithmImports/__init__.pyi
AlgorithmImports/py.typed
Common/__init__.py
Common/py.typed
Common/Data/__init__.py
Common/Data/Consolidators/__init__.py
Common/Data/Consolidators/__init__.pyi
Common/Util/__init__.py
Common/Util/__init__.pyi
Internal/__init__.py
Internal/__init__.pyi
Internal/py.typed
Internal/Runtime/__init__.py
Internal/Runtime/CompilerHelpers/__init__.py
Internal/Runtime/InteropServices/__init__.py
Internal/Win32/__init__.py
Internal/Win32/SafeHandles/__init__.py
MS/__init__.py
MS/py.typed
MS/Internal/__init__.py
MS/Internal/Xml/__init__.py
MS/Internal/Xml/Linq/__init__.py
MS/Internal/Xml/Linq/ComponentModel/__init__.py
Microsoft/__init__.py
Microsoft/py.typed
Microsoft/Win32/__init__.py
Microsoft/Win32/SafeHandles/__init__.py
Microsoft/Win32/SafeHandles/__init__.pyi
QuantConnect/__init__.py
QuantConnect/__init__.pyi
QuantConnect/py.typed
QuantConnect/Algorithm/__init__.py
QuantConnect/Algorithm/__init__.pyi
QuantConnect/Algorithm/Framework/__init__.py
QuantConnect/Algorithm/Framework/__init__.pyi
QuantConnect/Algorithm/Framework/Alphas/__init__.py
QuantConnect/Algorithm/Framework/Alphas/__init__.pyi
QuantConnect/Algorithm/Framework/Alphas/Analysis/__init__.py
QuantConnect/Algorithm/Framework/Alphas/Analysis/__init__.pyi
QuantConnect/Algorithm/Framework/Alphas/Serialization/__init__.py
QuantConnect/Algorithm/Framework/Alphas/Serialization/__init__.pyi
QuantConnect/Algorithm/Framework/Execution/__init__.py
QuantConnect/Algorithm/Framework/Execution/__init__.pyi
QuantConnect/Algorithm/Framework/Portfolio/__init__.py
QuantConnect/Algorithm/Framework/Portfolio/__init__.pyi
QuantConnect/Algorithm/Framework/Portfolio/SignalExports/__init__.py
QuantConnect/Algorithm/Framework/Portfolio/SignalExports/__init__.pyi
QuantConnect/Algorithm/Framework/Risk/__init__.py
QuantConnect/Algorithm/Framework/Risk/__init__.pyi
QuantConnect/Algorithm/Framework/Selection/__init__.py
QuantConnect/Algorithm/Framework/Selection/__init__.pyi
quantconnect_stubs-17508.dist-info/METADATA
quantconnect_stubs-17508.dist-info/WHEEL
quantconnect_stubs-17508.dist-info/top_level.txt
quantconnect_stubs-17508.dist-info/RECORD
