Metadata-Version: 2.4
Name: quantconnect-stubs
Version: 17508
Summary: Type stubs for QuantConnect's Lean
Home-page: https://github.com/QuantConnect/quantconnect-stubs-generator
Author: QuantConnect
Author-email: support@quantconnect.com
Classifier: Development Status :: 5 - Production/Stable
Classifier: Intended Audience :: Developers
Classifier: Intended Audience :: Financial and Insurance Industry
Classifier: License :: OSI Approved :: Apache Software License
Classifier: Programming Language :: Python :: 3
Requires-Dist: pandas
Requires-Dist: matplotlib
Dynamic: author
Dynamic: author-email
Dynamic: classifier
Dynamic: description
Dynamic: description-content-type
Dynamic: home-page
Dynamic: requires-dist
Dynamic: summary
